{
	"presentations":
	{
		"2013-10-10-wba1-kickoff/index.html":
		{
			"title" : "WBA1 Kickoff",
			"authors" : ["Prof. Christian Noss", "Volker Schäfer"]
		},
		"2013-10-10-brackets-basics/index.html":
		{
			"title" : "Einführung: Brackets",
			"authors" : ["Martin Baljan"]
		},
		"2013-10-10-git/index.html":
		{
			"title" : "Einführung: Git & GitHub",
			"authors" : ["Dominik Schilling", "Christoph Jerolimov"]
		},
		"2013-10-17-html-basics-gruppe13/index.html":
		{
			"title" : "HTML Basics (1)",
			"authors" : ["Peter Wagner", "Maik Güldenmeister", "Robert xxx"]
		},
		"2013-10-17-html-basics-gruppe2/index.html":
		{
			"title" : "HTML Basics (2)",
			"authors" : ["Muhamed Fazlic", "Minh Duc Bui", "Manuel Sorg"]
		},
		"2013-10-17-html-advanced-gruppe1/index.html":
		{
			"title" : "HTML Advanced & HTML5 (1)",
			"authors" : ["Dennis Dubbert", "Alexander Jan Müller"]
		},
		"2013-10-17-HTML-Advanced-Gruppe-2/index.html":
		{
			"title" : "HTML Advanced & HTML5 (2)",
			"authors" : ["Vsevolod Küppers", "Thomas Friesen", "Sercan Kücükköse"]
		},
		"2013-10-17-html-uebungen/index.html":
		{
			"title" : "HTML Übungen",
			"authors" : ["Martin Baljan", "Dominik Schilling", "Christoph Jerolimov"]
		}
	}
}
